MANIFEST.in
README.txt
setup.py
usuarioapppackagegeo/__init__.py
usuarioapppackagegeo/forms.py
usuarioapppackagegeo/models.py
usuarioapppackagegeo/nav.py
usuarioapppackagegeo.egg-info/PKG-INFO
usuarioapppackagegeo.egg-info/SOURCES.txt
usuarioapppackagegeo.egg-info/dependency_links.txt
usuarioapppackagegeo.egg-info/top_level.txt