Metadata-Version: 1.0
Name: usuarioapppackagegeo
Version: 0.0.1
Summary: Mi libreria geo
Home-page: https://github.com/hernandt80/geo
Author: Hernan DT80
Author-email: hernan.dt80@gmail.com
License: MIT
Keywords: geo,hernandt80
Platform: UNKNOWN
